lacia-0.2.6.dist-info/METADATA
lacia-0.2.6.dist-info/WHEEL
lacia-0.2.6.dist-info/entry_points.txt
lacia-0.2.6.dist-info/licenses/LICENSE
lacia/__init__.py
lacia/builtins/authentication.py
lacia/core/__init__.py
lacia/core/abcbase.py
lacia/core/core.py
lacia/core/proxy.py
lacia/exception.py
lacia/logger.py
lacia/network/__init__.py
lacia/network/abcbase.py
lacia/network/client/__init__.py
lacia/network/client/aiohttp.py
lacia/network/server/__init__.py
lacia/network/server/aiohttp.py
lacia/network/server/starlette.py
lacia/standard/__init__.py
lacia/standard/abcbase.py
lacia/standard/execute.py
lacia/standard/jsonast/__init__.py
lacia/standard/jsonast/impl.py
lacia/standard/jsonast/runtime.py
lacia/types.py
lacia/utils/hook.py
lacia/utils/tool.py
lacia-0.2.6.dist-info/RECORD
