Metadata-Version: 2.1
Name: lacia
Version: 0.2.6
Summary: A modern `Json-Rpc/Bson-Rpc` implementation, compatible with `Json-Rpc Ast` and `Json-Rpc 2.0` and `Json-Rpc X`, supports multiple network protocols and backend frameworks and supports bidirectional calls.
Author-Email: luxuncang <luxuncang@qq.com>
License: MIT
Classifier: Typing :: Typed
Classifier: Development Status :: 5 - Production/Stable
Classifier: Programming Language :: Python :: 3.10
Classifier: Programming Language :: Python :: 3.11
Classifier: Programming Language :: Python :: 3.12
Classifier: Operating System :: OS Independent
Project-URL: repository, https://github.com/LaciaProject/lacia
Requires-Python: >=3.10
Requires-Dist: richuru>=0.1.1
Requires-Dist: nest-asyncio>=1.5.8
Requires-Dist: aiohttp>=3.8.6
Requires-Dist: orjson>=3.9.10
Requires-Dist: bson>=0.5.10
Requires-Dist: typing-extensions>=4.8.0
Provides-Extra: starlette
Requires-Dist: starlette>=0.37.2; extra == "starlette"
Provides-Extra: uvicorn
Requires-Dist: uvicorn[standard]>=0.30.1; extra == "uvicorn"
Provides-Extra: fastapi
Requires-Dist: fastapi>=0.111.0; extra == "fastapi"
